src/Clustering.py
src/CodonsToAminos.py
src/Filtrados.py
src/Format_DF.py
src/GetEntropy.py
src/GetEntropySurface.py
src/Interpolation.py
src/NumericalSort.py
src/PlotEntropyPosition.py
src/PlotPopularDecay.py
src/ReadData.py
src/TSNE_exp.py
src/__init__.py
src/calculateGumbel.py
src/clusteringThread.py
src/codonDecayClass.py
src/dialogError.py
src/dialogInterpolation.py
src/dialogOK.py
src/dialogPositions.py
src/lvrvClass.py
src/lvrvThread.py
src/pcaClass.py
src/threadPCA.py
src/threadsOpenClass.py
src/threadsPlotClass.py
src/tsneClass.py
src/tsneThreadProcess.py
src/vev.py
src/buttons_and_background/Cancel.png
src/buttons_and_background/Clustering.png
src/buttons_and_background/Codon Decay.png
src/buttons_and_background/Error.png
src/buttons_and_background/Error2.png
src/buttons_and_background/Exit.png
src/buttons_and_background/Gumbel.png
src/buttons_and_background/ImageICON.jpg
src/buttons_and_background/Interpolation.png
src/buttons_and_background/LVRV.png
src/buttons_and_background/Load File.png
src/buttons_and_background/Load Folder.png
src/buttons_and_background/Loading.gif
src/buttons_and_background/Ok.png
src/buttons_and_background/PCA.png
src/buttons_and_background/Plot Entropy Surface.png
src/buttons_and_background/Plot Entropy x Position.png
src/buttons_and_background/Plot!.png
src/buttons_and_background/Refresh.png
src/buttons_and_background/Vacio.png
src/buttons_and_background/__init__.py
src/buttons_and_background/background.png
src/buttons_and_background/background2.png
src/buttons_and_background/background3.jpg
src/buttons_and_background/baseBackground.png
src/buttons_and_background/home.png
src/buttons_and_background/t-SNE.png
src/data_experiments/__init__.py
src/exports/__init__.py
src/logs/__init__.py
src/plot_images/__init__.py
src/ui_files/__init__.py
src/ui_files/dialogError.ui
src/ui_files/dialogOK.ui
src/ui_files/dialogPositions.ui
src/ui_files/interpolateDialog.ui
src/ui_files/mainwindow.ui
src/ui_files/pca.ui
vev_fing-1.1.10.dist-info/METADATA
vev_fing-1.1.10.dist-info/WHEEL
vev_fing-1.1.10.dist-info/entry_points.txt
vev_fing-1.1.10.dist-info/top_level.txt
vev_fing-1.1.10.dist-info/RECORD
