Metadata-Version: 2.1
Name: vev-fing
Version: 1.1.10
Summary: Visualization and Evolution of ARN Virus
Home-page: UNKNOWN
Author: Federico Aicardi,Rodrigo Cespedes
Author-email: vev-fing@gmail.com
License: MIT
Platform: UNKNOWN
Classifier: License :: OSI Approved :: MIT License
Classifier: Programming Language :: Python :: 3.6
Requires-Python: >=3.6
Requires-Dist: matplotlib (==3.2.1)
Requires-Dist: numpy (==1.18.4)
Requires-Dist: pandas (==0.25.3)
Requires-Dist: Pillow (==7.1.2)
Requires-Dist: scikit-learn (==0.22.2.post1)
Requires-Dist: scipy (==1.4.1)
Requires-Dist: pyqt5 (==5.15)
Requires-Dist: pyqtchart (==5.15)
Requires-Dist: dnspython (==1.16.0)
Requires-Dist: fastparquet (==0.4.0)
Requires-Dist: pymongo (==3.11.0)
Requires-Dist: pyarrow (==0.16.0)
Requires-Dist: jsonschema (==3.2.0)
Requires-Dist: pyts (==0.11.0)
Requires-Dist: tslearn (==0.4.1)
